datalizer/__init__.py
datalizer/cleaner.py
datalizer/loader.py
datalizer/preprocessor.py
datalizer/utils.py
datalizer-0.1.1.dist-info/licenses/LICENSE.txt
datalizer-0.1.1.dist-info/METADATA
datalizer-0.1.1.dist-info/WHEEL
datalizer-0.1.1.dist-info/top_level.txt
datalizer-0.1.1.dist-info/RECORD
