Metadata-Version: 2.4
Name: datalizer
Version: 0.1.1
Summary: Datalizer - A Python package for exploring, cleaning, and preparing numerical datasets.
Author: Eörs Szathmáry, Péter Osztobányi, Réka Kovács
Maintainer-email: Eörs Szathmáry <szathmary.eors@hallgato.itk.ppke.hu>
License: MIT License
Project-URL: Homepage, https://github.com/eorsjr/datalizer-scipy
Classifier: Programming Language :: Python :: 3
Classifier: Operating System :: OS Independent
Classifier: License :: OSI Approved :: MIT License
Classifier: Topic :: Scientific/Engineering
Requires-Python: >=3.10
License-File: LICENSE.txt
Requires-Dist: pandas>=2.0.0
Requires-Dist: numpy>=1.25.2
Requires-Dist: scikit-learn>=1.0.0
Dynamic: license-file
